pymedusa_zip/pymedusa_zip.cpython-311-x86_64-linux-gnu.so
medusa_zip-0.0.9.dist-info/top_level.txt
medusa_zip-0.0.9.dist-info/LICENSE
medusa_zip-0.0.9.dist-info/RECORD
medusa_zip-0.0.9.dist-info/WHEEL
medusa_zip-0.0.9.dist-info/METADATA
medusa_zip/py.typed
medusa_zip/destination.py
medusa_zip/merge.pyi
medusa_zip/crawl.py
medusa_zip/zip.pyi
medusa_zip/__init__.pyi
medusa_zip/merge.py
medusa_zip/destination.pyi
medusa_zip/__init__.py
medusa_zip/zip.py
medusa_zip/crawl.pyi
