Metadata-Version: 2.1
Name: medusa-zip
Version: 0.0.9
Summary: High-performance parallelized implementations of common zip file operations.
Author-email: Danny McClanahan <dmcC2@hypnicjerk.ai>
License: Apache-2.0
Project-URL: Homepage, https://github.com/cosmicexplorer/medusa-zip
Project-URL: Repository, https://github.com/cosmicexplorer/medusa-zip
Project-URL: Bug Tracker, https://github.com/cosmicexplorer/medusa-zip/issues
Keywords: zip,rust,fs,file,archive,parallel,pyo3
Classifier: License :: OSI Approved :: Apache Software License
Classifier: Intended Audience :: Developers
Classifier: Development Status :: 2 - Pre-Alpha
Classifier: Programming Language :: Python :: 3
Classifier: Programming Language :: Python :: 3.7
Classifier: Programming Language :: Python :: 3.8
Classifier: Programming Language :: Python :: 3.9
Classifier: Programming Language :: Python :: 3.10
Classifier: Programming Language :: Python :: 3.11
Classifier: Programming Language :: Rust
Classifier: Operating System :: POSIX
Classifier: Operating System :: POSIX :: Linux
Classifier: Operating System :: Unix
Classifier: Operating System :: MacOS :: MacOS X
Classifier: Operating System :: Microsoft :: Windows
Classifier: Programming Language :: Python :: Implementation :: CPython
Classifier: Programming Language :: Python :: Implementation :: PyPy
Classifier: Topic :: Software Development :: Build Tools
Classifier: Topic :: File Formats
Classifier: Topic :: System :: Archiving :: Compression
Classifier: Topic :: System :: Archiving :: Packaging
Classifier: Topic :: System :: Software Distribution
Classifier: Topic :: System :: Filesystems
Classifier: Topic :: Utilities
Classifier: Typing :: Typed
Requires-Python: >=3.7
License-File: LICENSE
Provides-Extra: asyncio
Provides-Extra: sync
